multiplierBlock.sv
module multiplierBlock #(
    parameter int WIDTH = 16
)(
    input  logic        clk,
    input  logic        rst_n,
    input  logic signed [WIDTH-1:0] a,
    input  logic signed [WIDTH-1:0] b,
    output logic signed [WIDTH-1:0] aOut,
    output logic signed [WIDTH-1:0] bOut,
    output logic signed [2*WIDTH-1:0] partialSum
);

always_ff @(posedge clk) begin
    if (!rst_n) begin
        partialSum <= 0;
        aOut   <= 0;
        bOut   <= 0;
    end else begin
        partialSum <= partialSum + a * b;
        aOut   <= a;
        bOut   <= b; 
    end   
end

endmodule

systolicArray.sv
module systolicArray #(
    parameter int WIDTH = 16,
    parameter int N = 3
) (
    input  logic        clk,
    input  logic        rst_n,
    input  logic signed [WIDTH-1:0] row[N]   ,
    input  logic signed [WIDTH-1:0] col[N]   ,
    output logic signed [2*WIDTH-1:0] resultMatrix [N][N]
);

logic [WIDTH-1:0] horizontalData [N:0][N:0];
logic [WIDTH-1:0] verticalData   [N:0][N:0];

genvar i, j;
generate
    for (i = 0; i < N; i = i + 1) begin : row_loop
        for (j = 0; j < N; j = j + 1) begin : col_loop
            
            // Initialize the first row and first column of the systolic array (this is to feed in the data)
            if (i==0) begin
                assign verticalData[i][j] = col[j];
            end
            if (j==0) begin
                assign horizontalData[i][j] = row[i];
            end
            
            // Instantiate multiplier blocks and their interconnections
            multiplierBlock mb (
                .clk   (clk),
                .rst_n (rst_n),
                .a     (horizontalData[i][j]),
                .b     (verticalData[i][j]),
                .aOut  (horizontalData[i][j+1]),
                .bOut  (verticalData[i+1][j]),
                .partialSum(resultMatrix[i][j])
            );

        end
    end
endgenerate

endmodule

dataOrchestrator.sv
module dataOrchestrator #(
    parameter int WIDTH = 16,
    parameter int N = 3
)(
    input  logic        clk,
    input  logic        rst_n,
    input  logic signed [WIDTH-1:0] matrixA [N][N],
    input  logic signed [WIDTH-1:0] matrixB [N][N],
    output logic signed [WIDTH-1:0] row     [N]   ,
    output logic signed [WIDTH-1:0] col     [N]   
);

logic [N:0] counter;

// Not fully parameterized yet, for N=3 only
always_ff @(posedge clk) begin
    
    // Set all outputs to 0 on reset
    if (!rst_n) begin
        counter  <= 4'd0;
        for (int i = 0; i < N; i = i + 1) begin
            row[i] <= 0;
            col[i] <= 0;
        end
    
    // Begin Data Orchestration
    end else begin
        counter <= counter + 1;

        if (counter >= 0 && counter < 3) begin
            row[0]  <= matrixA[0][counter];
            col[0]  <= matrixB[counter][0];
        end else begin 
            row[0]  <= 0;
            col[0]  <= 0;
        end
        if (counter >= 1 && counter < 4) begin
            row[1]  <= matrixA[1][counter - 1];
            col[1]  <= matrixB[counter - 1][1];
        end else begin 
            row[1]  <= 0;
            col[1]  <= 0;
        end
        if (counter >= 2 && counter < 5) begin
            row[2] <= matrixA[2][counter - 2];
            col[2] <= matrixB[counter - 2][2];
        end else begin 
            row[2] <= 0;
            col[2] <= 0;
        end
        
    end
end

endmodule

matrixMultiplierSmall.sv
module matrixMultiplierSmall #(
    parameter int WIDTH = 6,
    parameter int N = 3
)(
    input  logic        clk,
    input  logic        rst_n,
    input  logic signed [WIDTH-1:0] matrixA [N][N],
    input  logic signed [WIDTH-1:0] matrixB [N][N],
    output logic signed [2*WIDTH-1:0] resultMatrix [N][N]
);
    
    // Needed for internal connections, sadly looks like the synthesizer isn'st smart enough to optimize these away
    logic signed [WIDTH-1:0] rowData [N];
    logic signed [WIDTH-1:0] colData [N];
    
    dataOrchestrator #(
        .WIDTH(WIDTH),
        .N(N)
    ) dataOrch (
        .clk      (clk),
        .rst_n    (rst_n),
        .matrixA  (matrixA),
        .matrixB  (matrixB),
        .row      (rowData),
        .col      (colData)
    );

    systolicArray #(
        .WIDTH(WIDTH),
        .N(N)
    ) systolicArr (
        .clk          (clk),
        .rst_n        (rst_n),
        .row          (rowData),
        .col          (colData),
        .resultMatrix (resultMatrix)
    );
    
endmodule

tb_matrixMultiplierSmall.sv
// tb_matrixMultiplierSmall.sv
`timescale 1ns/1ps

module tb_matrixMultiplierSmall;

  // match the DUT defaults; change if you compiled DUT with other params
  localparam int WIDTH = 16;
  localparam int N     = 3;

  // clock / reset
  logic clk;
  logic rst_n;

  // DUT I/O
  logic signed [WIDTH-1:0] matrixA [N][N];
  logic signed [WIDTH-1:0] matrixB [N][N];
  logic signed [2*WIDTH-1:0] resultMatrix [N][N];

  // instantiate DUT
  matrixMultiplierSmall #(
    .WIDTH(WIDTH),
    .N(N)
  ) dut (
    .clk         (clk),
    .rst_n       (rst_n),
    .matrixA     (matrixA),
    .matrixB     (matrixB),
    .resultMatrix(resultMatrix)
  );

  // clock generator: 10ns period
  initial clk = 0;
  always #5 clk = ~clk;

  // test stimulus
  initial begin
    // waveform + tidy
    $dumpfile("tb_matrixMultiplierSmall.vcd");
    $dumpvars(0, tb_matrixMultiplierSmall);

    // initialize
    rst_n = 0;
    for (int i = 0; i < N; i++)
      for (int j = 0; j < N; j++) begin
        matrixA[i][j] = '0;
        matrixB[i][j] = '0;
      end

    rst_n = 0;

    // Set matrices during reset
    matrixA[0] = '{ 1,  2,  3 };
    matrixA[1] = '{ 4,  5,  6 };
    matrixA[2] = '{ 7,  8,  9 };

    matrixB[0] = '{ 1,  0,  0 };
    matrixB[1] = '{ 0,  1,  0 };
    matrixB[2] = '{ 0,  0,  1 };

    #20;
    rst_n = 1;

    // give the DUT several cycles to process (depends on real implementation latency)
    #100;

    // print out resultMatrix
    $display("---- resultMatrix ----");
    for (int i = 0; i < N; i++) begin
      for (int j = 0; j < N; j++) begin
        $write("%0d\t", resultMatrix[i][j]);
      end
      $write("\n");
    end
    $display("----------------------");

    #10;
    $finish;
  end

endmodule

ModelSim Stuff/tb_matrixMultiplierSmall.vcd
$date
	Thu Nov 13 19:50:05 2025
$end
$version
	ModelSim Version 10.5b
$end
$timescale
	1ps
$end

$scope module tb_matrixMultiplierSmall $end
$var parameter 32 ! WIDTH $end
$var parameter 32 " N $end
$var reg 1 # clk $end
$var reg 1 $ rst_n $end

$scope module dut $end
$var parameter 32 % WIDTH $end
$var parameter 32 & N $end
$var wire 1 ' clk $end
$var wire 1 ( rst_n $end

$scope module dataOrch $end
$var parameter 32 ) WIDTH $end
$var parameter 32 * N $end
$var wire 1 ' clk $end
$var wire 1 ( rst_n $end
$var reg 4 + counter [3:0] $end
$upscope $end

$scope module systolicArr $end
$var parameter 32 , WIDTH $end
$var parameter 32 - N $end
$var wire 1 ' clk $end
$var wire 1 ( rst_n $end

$scope begin row_loop[2] $end
$var parameter 32 . i $end

$scope begin col_loop[2] $end
$var parameter 32 / j $end

$scope begin genblk1 $end
$upscope $end

$scope begin genblk2 $end
$upscope $end

$scope module mb $end
$var parameter 32 0 WIDTH $end
$var wire 1 ' clk $end
$var wire 1 ( rst_n $end
$var wire 1 1 a [15] $end
$var wire 1 2 a [14] $end
$var wire 1 3 a [13] $end
$var wire 1 4 a [12] $end
$var wire 1 5 a [11] $end
$var wire 1 6 a [10] $end
$var wire 1 7 a [9] $end
$var wire 1 8 a [8] $end
$var wire 1 9 a [7] $end
$var wire 1 : a [6] $end
$var wire 1 ; a [5] $end
$var wire 1 < a [4] $end
$var wire 1 = a [3] $end
$var wire 1 > a [2] $end
$var wire 1 ? a [1] $end
$var wire 1 @ a [0] $end
$var wire 1 A b [15] $end
$var wire 1 B b [14] $end
$var wire 1 C b [13] $end
$var wire 1 D b [12] $end
$var wire 1 E b [11] $end
$var wire 1 F b [10] $end
$var wire 1 G b [9] $end
$var wire 1 H b [8] $end
$var wire 1 I b [7] $end
$var wire 1 J b [6] $end
$var wire 1 K b [5] $end
$var wire 1 L b [4] $end
$var wire 1 M b [3] $end
$var wire 1 N b [2] $end
$var wire 1 O b [1] $end
$var wire 1 P b [0] $end
$var reg 16 Q aOut [15:0] $end
$var reg 16 R bOut [15:0] $end
$var reg 32 S partialSum [31:0] $end
$upscope $end
$upscope $end

$scope begin col_loop[1] $end
$var parameter 32 T j $end

$scope begin genblk1 $end
$upscope $end

$scope begin genblk2 $end
$upscope $end

$scope module mb $end
$var parameter 32 U WIDTH $end
$var wire 1 ' clk $end
$var wire 1 ( rst_n $end
$var wire 1 V a [15] $end
$var wire 1 W a [14] $end
$var wire 1 X a [13] $end
$var wire 1 Y a [12] $end
$var wire 1 Z a [11] $end
$var wire 1 [ a [10] $end
$var wire 1 \ a [9] $end
$var wire 1 ] a [8] $end
$var wire 1 ^ a [7] $end
$var wire 1 _ a [6] $end
$var wire 1 ` a [5] $end
$var wire 1 a a [4] $end
$var wire 1 b a [3] $end
$var wire 1 c a [2] $end
$var wire 1 d a [1] $end
$var wire 1 e a [0] $end
$var wire 1 f b [15] $end
$var wire 1 g b [14] $end
$var wire 1 h b [13] $end
$var wire 1 i b [12] $end
$var wire 1 j b [11] $end
$var wire 1 k b [10] $end
$var wire 1 l b [9] $end
$var wire 1 m b [8] $end
$var wire 1 n b [7] $end
$var wire 1 o b [6] $end
$var wire 1 p b [5] $end
$var wire 1 q b [4] $end
$var wire 1 r b [3] $end
$var wire 1 s b [2] $end
$var wire 1 t b [1] $end
$var wire 1 u b [0] $end
$var reg 16 v aOut [15:0] $end
$var reg 16 w bOut [15:0] $end
$var reg 32 x partialSum [31:0] $end
$upscope $end
$upscope $end

$scope begin col_loop[0] $end
$var parameter 32 y j $end

$scope begin genblk1 $end
$upscope $end

$scope begin genblk2 $end
$upscope $end

$scope module mb $end
$var parameter 32 z WIDTH $end
$var wire 1 ' clk $end
$var wire 1 ( rst_n $end
$var wire 1 { a [15] $end
$var wire 1 | a [14] $end
$var wire 1 } a [13] $end
$var wire 1 ~ a [12] $end
$var wire 1 !! a [11] $end
$var wire 1 "! a [10] $end
$var wire 1 #! a [9] $end
$var wire 1 $! a [8] $end
$var wire 1 %! a [7] $end
$var wire 1 &! a [6] $end
$var wire 1 '! a [5] $end
$var wire 1 (! a [4] $end
$var wire 1 )! a [3] $end
$var wire 1 *! a [2] $end
$var wire 1 +! a [1] $end
$var wire 1 ,! a [0] $end
$var wire 1 -! b [15] $end
$var wire 1 .! b [14] $end
$var wire 1 /! b [13] $end
$var wire 1 0! b [12] $end
$var wire 1 1! b [11] $end
$var wire 1 2! b [10] $end
$var wire 1 3! b [9] $end
$var wire 1 4! b [8] $end
$var wire 1 5! b [7] $end
$var wire 1 6! b [6] $end
$var wire 1 7! b [5] $end
$var wire 1 8! b [4] $end
$var wire 1 9! b [3] $end
$var wire 1 :! b [2] $end
$var wire 1 ;! b [1] $end
$var wire 1 <! b [0] $end
$var reg 16 =! aOut [15:0] $end
$var reg 16 >! bOut [15:0] $end
$var reg 32 ?! partialSum [31:0] $end
$upscope $end
$upscope $end
$upscope $end

$scope begin row_loop[1] $end
$var parameter 32 @! i $end

$scope begin col_loop[2] $end
$var parameter 32 A! j $end

$scope begin genblk1 $end
$upscope $end

$scope begin genblk2 $end
$upscope $end

$scope module mb $end
$var parameter 32 B! WIDTH $end
$var wire 1 ' clk $end
$var wire 1 ( rst_n $end
$var wire 1 C! a [15] $end
$var wire 1 D! a [14] $end
$var wire 1 E! a [13] $end
$var wire 1 F! a [12] $end
$var wire 1 G! a [11] $end
$var wire 1 H! a [10] $end
$var wire 1 I! a [9] $end
$var wire 1 J! a [8] $end
$var wire 1 K! a [7] $end
$var wire 1 L! a [6] $end
$var wire 1 M! a [5] $end
$var wire 1 N! a [4] $end
$var wire 1 O! a [3] $end
$var wire 1 P! a [2] $end
$var wire 1 Q! a [1] $end
$var wire 1 R! a [0] $end
$var wire 1 S! b [15] $end
$var wire 1 T! b [14] $end
$var wire 1 U! b [13] $end
$var wire 1 V! b [12] $end
$var wire 1 W! b [11] $end
$var wire 1 X! b [10] $end
$var wire 1 Y! b [9] $end
$var wire 1 Z! b [8] $end
$var wire 1 [! b [7] $end
$var wire 1 \! b [6] $end
$var wire 1 ]! b [5] $end
$var wire 1 ^! b [4] $end
$var wire 1 _! b [3] $end
$var wire 1 `! b [2] $end
$var wire 1 a! b [1] $end
$var wire 1 b! b [0] $end
$var reg 16 c! aOut [15:0] $end
$var reg 16 d! bOut [15:0] $end
$var reg 32 e! partialSum [31:0] $end
$upscope $end
$upscope $end

$scope begin col_loop[1] $end
$var parameter 32 f! j $end

$scope begin genblk1 $end
$upscope $end

$scope begin genblk2 $end
$upscope $end

$scope module mb $end
$var parameter 32 g! WIDTH $end
$var wire 1 ' clk $end
$var wire 1 ( rst_n $end
$var wire 1 h! a [15] $end
$var wire 1 i! a [14] $end
$var wire 1 j! a [13] $end
$var wire 1 k! a [12] $end
$var wire 1 l! a [11] $end
$var wire 1 m! a [10] $end
$var wire 1 n! a [9] $end
$var wire 1 o! a [8] $end
$var wire 1 p! a [7] $end
$var wire 1 q! a [6] $end
$var wire 1 r! a [5] $end
$var wire 1 s! a [4] $end
$var wire 1 t! a [3] $end
$var wire 1 u! a [2] $end
$var wire 1 v! a [1] $end
$var wire 1 w! a [0] $end
$var wire 1 x! b [15] $end
$var wire 1 y! b [14] $end
$var wire 1 z! b [13] $end
$var wire 1 {! b [12] $end
$var wire 1 |! b [11] $end
$var wire 1 }! b [10] $end
$var wire 1 ~! b [9] $end
$var wire 1 !" b [8] $end
$var wire 1 "" b [7] $end
$var wire 1 #" b [6] $end
$var wire 1 $" b [5] $end
$var wire 1 %" b [4] $end
$var wire 1 &" b [3] $end
$var wire 1 '" b [2] $end
$var wire 1 (" b [1] $end
$var wire 1 )" b [0] $end
$var reg 16 *" aOut [15:0] $end
$var reg 16 +" bOut [15:0] $end
$var reg 32 ," partialSum [31:0] $end
$upscope $end
$upscope $end

$scope begin col_loop[0] $end
$var parameter 32 -" j $end

$scope begin genblk1 $end
$upscope $end

$scope begin genblk2 $end
$upscope $end

$scope module mb $end
$var parameter 32 ." WIDTH $end
$var wire 1 ' clk $end
$var wire 1 ( rst_n $end
$var wire 1 /" a [15] $end
$var wire 1 0" a [14] $end
$var wire 1 1" a [13] $end
$var wire 1 2" a [12] $end
$var wire 1 3" a [11] $end
$var wire 1 4" a [10] $end
$var wire 1 5" a [9] $end
$var wire 1 6" a [8] $end
$var wire 1 7" a [7] $end
$var wire 1 8" a [6] $end
$var wire 1 9" a [5] $end
$var wire 1 :" a [4] $end
$var wire 1 ;" a [3] $end
$var wire 1 <" a [2] $end
$var wire 1 =" a [1] $end
$var wire 1 >" a [0] $end
$var wire 1 ?" b [15] $end
$var wire 1 @" b [14] $end
$var wire 1 A" b [13] $end
$var wire 1 B" b [12] $end
$var wire 1 C" b [11] $end
$var wire 1 D" b [10] $end
$var wire 1 E" b [9] $end
$var wire 1 F" b [8] $end
$var wire 1 G" b [7] $end
$var wire 1 H" b [6] $end
$var wire 1 I" b [5] $end
$var wire 1 J" b [4] $end
$var wire 1 K" b [3] $end
$var wire 1 L" b [2] $end
$var wire 1 M" b [1] $end
$var wire 1 N" b [0] $end
$var reg 16 O" aOut [15:0] $end
$var reg 16 P" bOut [15:0] $end
$var reg 32 Q" partialSum [31:0] $end
$upscope $end
$upscope $end
$upscope $end

$scope begin row_loop[0] $end
$var parameter 32 R" i $end

$scope begin col_loop[2] $end
$var parameter 32 S" j $end

$scope begin genblk1 $end
$upscope $end

$scope begin genblk2 $end
$upscope $end

$scope module mb $end
$var parameter 32 T" WIDTH $end
$var wire 1 ' clk $end
$var wire 1 ( rst_n $end
$var wire 1 U" a [15] $end
$var wire 1 V" a [14] $end
$var wire 1 W" a [13] $end
$var wire 1 X" a [12] $end
$var wire 1 Y" a [11] $end
$var wire 1 Z" a [10] $end
$var wire 1 [" a [9] $end
$var wire 1 \" a [8] $end
$var wire 1 ]" a [7] $end
$var wire 1 ^" a [6] $end
$var wire 1 _" a [5] $end
$var wire 1 `" a [4] $end
$var wire 1 a" a [3] $end
$var wire 1 b" a [2] $end
$var wire 1 c" a [1] $end
$var wire 1 d" a [0] $end
$var wire 1 e" b [15] $end
$var wire 1 f" b [14] $end
$var wire 1 g" b [13] $end
$var wire 1 h" b [12] $end
$var wire 1 i" b [11] $end
$var wire 1 j" b [10] $end
$var wire 1 k" b [9] $end
$var wire 1 l" b [8] $end
$var wire 1 m" b [7] $end
$var wire 1 n" b [6] $end
$var wire 1 o" b [5] $end
$var wire 1 p" b [4] $end
$var wire 1 q" b [3] $end
$var wire 1 r" b [2] $end
$var wire 1 s" b [1] $end
$var wire 1 t" b [0] $end
$var reg 16 u" aOut [15:0] $end
$var reg 16 v" bOut [15:0] $end
$var reg 32 w" partialSum [31:0] $end
$upscope $end
$upscope $end

$scope begin col_loop[1] $end
$var parameter 32 x" j $end

$scope begin genblk1 $end
$upscope $end

$scope begin genblk2 $end
$upscope $end

$scope module mb $end
$var parameter 32 y" WIDTH $end
$var wire 1 ' clk $end
$var wire 1 ( rst_n $end
$var wire 1 z" a [15] $end
$var wire 1 {" a [14] $end
$var wire 1 |" a [13] $end
$var wire 1 }" a [12] $end
$var wire 1 ~" a [11] $end
$var wire 1 !# a [10] $end
$var wire 1 "# a [9] $end
$var wire 1 ## a [8] $end
$var wire 1 $# a [7] $end
$var wire 1 %# a [6] $end
$var wire 1 &# a [5] $end
$var wire 1 '# a [4] $end
$var wire 1 (# a [3] $end
$var wire 1 )# a [2] $end
$var wire 1 *# a [1] $end
$var wire 1 +# a [0] $end
$var wire 1 ,# b [15] $end
$var wire 1 -# b [14] $end
$var wire 1 .# b [13] $end
$var wire 1 /# b [12] $end
$var wire 1 0# b [11] $end
$var wire 1 1# b [10] $end
$var wire 1 2# b [9] $end
$var wire 1 3# b [8] $end
$var wire 1 4# b [7] $end
$var wire 1 5# b [6] $end
$var wire 1 6# b [5] $end
$var wire 1 7# b [4] $end
$var wire 1 8# b [3] $end
$var wire 1 9# b [2] $end
$var wire 1 :# b [1] $end
$var wire 1 ;# b [0] $end
$var reg 16 <# aOut [15:0] $end
$var reg 16 =# bOut [15:0] $end
$var reg 32 ># partialSum [31:0] $end
$upscope $end
$upscope $end

$scope begin col_loop[0] $end
$var parameter 32 ?# j $end

$scope begin genblk1 $end
$upscope $end

$scope begin genblk2 $end
$upscope $end

$scope module mb $end
$var parameter 32 @# WIDTH $end
$var wire 1 ' clk $end
$var wire 1 ( rst_n $end
$var wire 1 A# a [15] $end
$var wire 1 B# a [14] $end
$var wire 1 C# a [13] $end
$var wire 1 D# a [12] $end
$var wire 1 E# a [11] $end
$var wire 1 F# a [10] $end
$var wire 1 G# a [9] $end
$var wire 1 H# a [8] $end
$var wire 1 I# a [7] $end
$var wire 1 J# a [6] $end
$var wire 1 K# a [5] $end
$var wire 1 L# a [4] $end
$var wire 1 M# a [3] $end
$var wire 1 N# a [2] $end
$var wire 1 O# a [1] $end
$var wire 1 P# a [0] $end
$var wire 1 Q# b [15] $end
$var wire 1 R# b [14] $end
$var wire 1 S# b [13] $end
$var wire 1 T# b [12] $end
$var wire 1 U# b [11] $end
$var wire 1 V# b [10] $end
$var wire 1 W# b [9] $end
$var wire 1 X# b [8] $end
$var wire 1 Y# b [7] $end
$var wire 1 Z# b [6] $end
$var wire 1 [# b [5] $end
$var wire 1 \# b [4] $end
$var wire 1 ]# b [3] $end
$var wire 1 ^# b [2] $end
$var wire 1 _# b [1] $end
$var wire 1 `# b [0] $end
$var reg 16 a# aOut [15:0] $end
$var reg 16 b# bOut [15:0] $end
$var reg 32 c# partialSum [31:0] $end
$upscope $end
$upscope $end
$upscope $end
$upscope $end
$upscope $end
$upscope $end
$enddefinitions $end
#0
$dumpvars
0#
0$
bx +
bx a#
bx b#
bx c#
bx <#
bx =#
bx >#
bx u"
bx v"
bx w"
bx O"
bx P"
bx Q"
bx *"
bx +"
bx ,"
bx c!
bx d!
bx e!
bx =!
bx >!
bx ?!
bx v
bx w
bx x
bx Q
bx R
bx S
b10000 !
b11 "
b10000 %
b11 &
b10000 )
b11 *
b10000 ,
b11 -
b0 R"
b0 ?#
b10000 @#
b1 x"
b10000 y"
b10 S"
b10000 T"
b1 @!
b0 -"
b10000 ."
b1 f!
b10000 g!
b10 A!
b10000 B!
b10 .
b0 y
b10000 z
b1 T
b10000 U
b10 /
b10000 0
0'
0(
xP#
xO#
xN#
xM#
xL#
xK#
xJ#
xI#
xH#
xG#
xF#
xE#
xD#
xC#
xB#
xA#
x`#
x_#
x^#
x]#
x\#
x[#
xZ#
xY#
xX#
xW#
xV#
xU#
xT#
xS#
xR#
xQ#
x+#
x*#
x)#
x(#
x'#
x&#
x%#
x$#
x##
x"#
x!#
x~"
x}"
x|"
x{"
xz"
x;#
x:#
x9#
x8#
x7#
x6#
x5#
x4#
x3#
x2#
x1#
x0#
x/#
x.#
x-#
x,#
xd"
xc"
xb"
xa"
x`"
x_"
x^"
x]"
x\"
x["
xZ"
xY"
xX"
xW"
xV"
xU"
xt"
xs"
xr"
xq"
xp"
xo"
xn"
xm"
xl"
xk"
xj"
xi"
xh"
xg"
xf"
xe"
x>"
x="
x<"
x;"
x:"
x9"
x8"
x7"
x6"
x5"
x4"
x3"
x2"
x1"
x0"
x/"
xN"
xM"
xL"
xK"
xJ"
xI"
xH"
xG"
xF"
xE"
xD"
xC"
xB"
xA"
x@"
x?"
xw!
xv!
xu!
xt!
xs!
xr!
xq!
xp!
xo!
xn!
xm!
xl!
xk!
xj!
xi!
xh!
x)"
x("
x'"
x&"
x%"
x$"
x#"
x""
x!"
x~!
x}!
x|!
x{!
xz!
xy!
xx!
xR!
xQ!
xP!
xO!
xN!
xM!
xL!
xK!
xJ!
xI!
xH!
xG!
xF!
xE!
xD!
xC!
xb!
xa!
x`!
x_!
x^!
x]!
x\!
x[!
xZ!
xY!
xX!
xW!
xV!
xU!
xT!
xS!
x,!
x+!
x*!
x)!
x(!
x'!
x&!
x%!
x$!
x#!
x"!
x!!
x~
x}
x|
x{
x<!
x;!
x:!
x9!
x8!
x7!
x6!
x5!
x4!
x3!
x2!
x1!
x0!
x/!
x.!
x-!
xe
xd
xc
xb
xa
x`
x_
x^
x]
x\
x[
xZ
xY
xX
xW
xV
xu
xt
xs
xr
xq
xp
xo
xn
xm
xl
xk
xj
xi
xh
xg
xf
x@
x?
x>
x=
x<
x;
x:
x9
x8
x7
x6
x5
x4
x3
x2
x1
xP
xO
xN
xM
xL
xK
xJ
xI
xH
xG
xF
xE
xD
xC
xB
xA
$end
#5000
1#
1'
b0 +
b0 c#
b0 a#
b0 b#
b0 >#
b0 <#
b0 =#
b0 w"
b0 u"
b0 v"
b0 Q"
b0 O"
b0 P"
b0 ,"
b0 *"
b0 +"
b0 e!
b0 c!
b0 d!
b0 ?!
b0 =!
b0 >!
b0 x
b0 v
b0 w
b0 S
b0 Q
b0 R
0P
0O
0N
0M
0L
0K
0J
0I
0H
0G
0F
0E
0D
0C
0B
0A
0u
0t
0s
0r
0q
0p
0o
0n
0m
0l
0k
0j
0i
0h
0g
0f
0<!
0;!
0:!
09!
08!
07!
06!
05!
04!
03!
02!
01!
00!
0/!
0.!
0-!
0b!
0a!
0`!
0_!
0^!
0]!
0\!
0[!
0Z!
0Y!
0X!
0W!
0V!
0U!
0T!
0S!
0)"
0("
0'"
0&"
0%"
0$"
0#"
0""
0!"
0~!
0}!
0|!
0{!
0z!
0y!
0x!
0N"
0M"
0L"
0K"
0J"
0I"
0H"
0G"
0F"
0E"
0D"
0C"
0B"
0A"
0@"
0?"
0@
0?
0>
0=
0<
0;
0:
09
08
07
06
05
04
03
02
01
0e
0d
0c
0b
0a
0`
0_
0^
0]
0\
0[
0Z
0Y
0X
0W
0V
0R!
0Q!
0P!
0O!
0N!
0M!
0L!
0K!
0J!
0I!
0H!
0G!
0F!
0E!
0D!
0C!
0w!
0v!
0u!
0t!
0s!
0r!
0q!
0p!
0o!
0n!
0m!
0l!
0k!
0j!
0i!
0h!
0d"
0c"
0b"
0a"
0`"
0_"
0^"
0]"
0\"
0["
0Z"
0Y"
0X"
0W"
0V"
0U"
0+#
0*#
0)#
0(#
0'#
0&#
0%#
0$#
0##
0"#
0!#
0~"
0}"
0|"
0{"
0z"
0t"
0s"
0r"
0q"
0p"
0o"
0n"
0m"
0l"
0k"
0j"
0i"
0h"
0g"
0f"
0e"
0;#
0:#
09#
08#
07#
06#
05#
04#
03#
02#
01#
00#
0/#
0.#
0-#
0,#
0`#
0_#
0^#
0]#
0\#
0[#
0Z#
0Y#
0X#
0W#
0V#
0U#
0T#
0S#
0R#
0Q#
0,!
0+!
0*!
0)!
0(!
0'!
0&!
0%!
0$!
0#!
0"!
0!!
0~
0}
0|
0{
0>"
0="
0<"
0;"
0:"
09"
08"
07"
06"
05"
04"
03"
02"
01"
00"
0/"
0P#
0O#
0N#
0M#
0L#
0K#
0J#
0I#
0H#
0G#
0F#
0E#
0D#
0C#
0B#
0A#
#10000
0#
0'
#15000
1#
1'
#20000
1$
0#
1(
0'
#25000
1#
1'
b1 +
1`#
1P#
#30000
0#
0'
#35000
1#
1'
b10 +
b1 c#
b1 a#
b1 b#
1N"
1+#
1_#
1<"
0P#
1O#
#40000
0#
0'
#45000
1#
1'
b11 +
b111 c#
b10 a#
b11 b#
b1 <#
b100 Q"
b100 O"
b1 P"
1<!
1M"
1u!
1d"
0+#
1*#
1s"
1;#
1:#
19#
18#
17#
16#
15#
14#
13#
12#
11#
10#
1/#
1.#
1-#
1,#
0`#
1,!
1+!
1*!
1>"
1P#
#50000
0#
0'
#55000
1#
1'
b100 +
b1101 c#
b11 a#
b10 b#
b11111111111111111111111111111110 >#
b10 <#
b1111111111111111 =#
b10 w"
b1 u"
b10 v"
b10011 Q"
b101 O"
b11 P"
b100 *"
b111 ?!
b111 =!
b1 >!
1;!
1a!
1)"
1("
1'"
1&"
1%"
1$"
1#"
1""
1!"
1~!
1}!
1|!
1{!
1z!
1y!
1x!
0N"
1e
1d
1c
1P!
1w!
0d"
1c"
1+#
1t"
0s"
0;#
09#
08#
07#
06#
05#
04#
03#
02#
01#
00#
0/#
0.#
0-#
0,#
0_#
0+!
0*!
0>"
1="
0P#
0O#
#60000
0#
0'
#65000
1#
1'
b101 +
b0 a#
b0 b#
b100 >#
b11 <#
b10 =#
b100 w"
b10 u"
b1 v"
b11111 Q"
b110 O"
b10 P"
b11111111111111111111111111111011 ,"
b101 *"
b1111111111111111 +"
b1000 e!
b100 c!
b10 d!
b1010 ?!
b1 =!
b11 >!
b111 v
1@
1?
1>
0d
0c
1R!
0w!
1v!
1d"
0+#
0*#
1O
1u
1t
1s
1r
1q
1p
1o
1n
1m
1l
1k
1j
1i
1h
1g
1f
0<!
1b!
0a!
0)"
0'"
0&"
0%"
0$"
0#"
0""
0!"
0~!
0}!
0|!
0{!
0z!
0y!
0x!
0M"
1s"
1r"
1q"
1p"
1o"
1n"
1m"
1l"
1k"
1j"
1i"
1h"
1g"
1f"
1e"
0:#
0,!
1+!
1*!
1)!
1(!
1'!
1&!
1%!
1$!
1#!
1"!
1!!
1~
1}
1|
1{
0="
0<"
#70000
0#
0'
#75000
1#
1'
b110 +
b0 <#
b0 =#
b1 w"
b11 u"
b1111111111111111 v"
b0 O"
b0 P"
b111 ,"
b110 *"
b10 +"
b1101 e!
b101 c!
b1 d!
b110 ?!
b1111111111111110 =!
b10 >!
b11111111111111111111111111111111 x
b1 v
b1111111111111111 w
b1110 S
b111 Q
b10 R
1P
0O
0u
0s
0r
0q
0p
0o
0n
0m
0l
0k
0j
0i
0h
0g
0f
0;!
1a!
1`!
1_!
1^!
1]!
1\!
1[!
1Z!
1Y!
1X!
1W!
1V!
1U!
1T!
1S!
0("
0?
0>
0e
1d
1c
1b
1a
1`
1_
1^
1]
1\
1[
1Z
1Y
1X
1W
1V
0R!
1Q!
0v!
0u!
0d"
0c"
0t"
0s"
0r"
0q"
0p"
0o"
0n"
0m"
0l"
0k"
0j"
0i"
0h"
0g"
0f"
0e"
0+!
0*!
0)!
0(!
0'!
0&!
0%!
0$!
0#!
0"!
0!!
0~
0}
0|
0{
#80000
0#
0'
#85000
1#
1'
b111 +
b0 u"
b0 v"
b0 *"
b0 +"
b111 e!
b110 c!
b1111111111111111 d!
b0 =!
b0 >!
b11111111111111111111111111111011 x
b1111111111111110 v
b10 w
b1111 S
b1 Q
b1 R
1O
1N
1M
1L
1K
1J
1I
1H
1G
1F
1E
1D
1C
1B
1A
0t
0b!
0a!
0`!
0_!
0^!
0]!
0\!
0[!
0Z!
0Y!
0X!
0W!
0V!
0U!
0T!
0S!
0@
1?
1>
1=
1<
1;
1:
19
18
17
16
15
14
13
12
11
0d
0c
0b
0a
0`
0_
0^
0]
0\
0[
0Z
0Y
0X
0W
0V
0Q!
0P!
#90000
0#
0'
#95000
1#
1'
b1000 +
b0 c!
b0 d!
b0 v
b0 w
b10001 S
b1111111111111110 Q
b1111111111111111 R
0P
0O
0N
0M
0L
0K
0J
0I
0H
0G
0F
0E
0D
0C
0B
0A
0?
0>
0=
0<
0;
0:
09
08
07
06
05
04
03
02
01
#100000
0#
0'
#105000
1#
1'
b1001 +
b0 Q
b0 R
#110000
0#
0'
#115000
1#
1'
b1010 +
#120000
0#
0'
#125000
1#
1'
b1011 +
